Jakit/__init__.py
Jakit/app.py
Jakit/error_handler.py
Jakit/jakit_jobs.py
Jakit-0.9.dist-info/LICENSE
Jakit-0.9.dist-info/METADATA
Jakit-0.9.dist-info/WHEEL
Jakit-0.9.dist-info/top_level.txt
Jakit-0.9.dist-info/RECORD
